intset/__init__.py
intset/intset.py
intset/version.py
intset-1.0.0.dist-info/top_level.txt
intset-1.0.0.dist-info/DESCRIPTION.rst
intset-1.0.0.dist-info/metadata.json
intset-1.0.0.dist-info/RECORD
intset-1.0.0.dist-info/WHEEL
intset-1.0.0.dist-info/METADATA
